mrmd_bash/__init__.py
mrmd_bash/cli.py
mrmd_bash/server.py
mrmd_bash/types.py
mrmd_bash/worker.py
mrmd_bash-0.1.1.dist-info/METADATA
mrmd_bash-0.1.1.dist-info/WHEEL
mrmd_bash-0.1.1.dist-info/entry_points.txt
mrmd_bash-0.1.1.dist-info/RECORD
