Metadata-Version: 2.4
Name: mrmd-bash
Version: 0.1.1
Summary: MRP (MRMD Runtime Protocol) server for Bash
Author: MRMD Team
License: MIT
Keywords: bash,mrmd,mrp,notebook,runtime
Classifier: Development Status :: 3 - Alpha
Classifier: Environment :: Console
Classifier: Intended Audience :: Developers
Classifier: License :: OSI Approved :: MIT License
Classifier: Operating System :: POSIX
Classifier: Programming Language :: Python :: 3
Classifier: Programming Language :: Python :: 3.10
Classifier: Programming Language :: Python :: 3.11
Classifier: Programming Language :: Python :: 3.12
Classifier: Topic :: Software Development
Requires-Python: >=3.10
Requires-Dist: httpx>=0.24.0
Requires-Dist: sse-starlette>=1.6.0
Requires-Dist: starlette>=0.27.0
Requires-Dist: uvicorn>=0.22.0
Provides-Extra: dev
Requires-Dist: pytest-asyncio>=0.21; extra == 'dev'
Requires-Dist: pytest>=7.0; extra == 'dev'
Requires-Dist: ruff>=0.1.0; extra == 'dev'
